{
    "score": [
        0.36363636363636365
    ],
    "extracted": [
        0
    ],
    "abstract": [
        "monthly update - australian labour & employment - november 2017 ."
    ],
    "id": "254882.train",
    "article": [
        "message from the editor - in this edition of the update , we report on woolworths ' commitment to identify and address human rights risks in its australian supply chains . we then discuss a class action expected to be lodged by a trade union on behalf of thousands of underpaid independent contractors , and the australian bureau of statistics ' wage price index report for the september quarter 2017 . we then consider a fair work commission decision in which a large employer 's lawyers were denied permission to represent the employer in unfair dismissal proceedings . finally , we comment upon a decision of the federal court of australia in which significant civil penalties were imposed on an employer and the employer 's hr manager in relation to the underpayment of employees . ",
        "please see full publication below for more information . firefox recommends the pdf plugin for mac os x for viewing pdf documents in your browser . we can also show you legal updates using the google viewer ; however , you will need to be logged into google docs to view them . please choose one of the above to proceed !   "
    ]
}