{
    "score": [
        0.4
    ],
    "extracted": [
        0
    ],
    "abstract": [
        "tips for drawing backgrounds ."
    ],
    "id": "871182.train",
    "article": [
        "thomas romain is a terrific artist working in the anime industry in tokyo . previously , he showed how to draw detailed buildings . this time , we 're going to learn from him how to draw backgrounds . romain has an impressive resume , including art direction on symphogear and mecha design for space dandy . over numerous months , he 's been kind enough to share his insight and tips on twitter . his advice is wonderful and will no doubt make you a better artist . i think it 's great he takes him out to share his knowledge . ",
        "if you do n't follow romain on twitter , you should . for more , check out romain 's twitter account . you can also read an interview with him on robot-envy . this article was originally published on february 15 , 2016 . to contact the author of this post , write to bashcraftatkotaku . com or find him on twitter@brian _ ashcraft . kotaku east is your slice of asian internet culture , bringing you the latest talking points from japan , korea , china and beyond . tune in every morning from 4 am to 8 am . "
    ]
}